dogesec_commons/__init__.py
dogesec_commons/asgi.py
dogesec_commons/settings.py
dogesec_commons/urls.py
dogesec_commons/wsgi.py
dogesec_commons/identity/apps.py
dogesec_commons/identity/models.py
dogesec_commons/identity/serializers.py
dogesec_commons/identity/views.py
dogesec_commons/identity/migrations/0001_initial.py
dogesec_commons/identity/migrations/__init__.py
dogesec_commons/objects/__init__.py
dogesec_commons/objects/apps.py
dogesec_commons/objects/conf.py
dogesec_commons/objects/db_view_creator.py
dogesec_commons/objects/helpers.py
dogesec_commons/objects/views.py
dogesec_commons/stixifier/__init__.py
dogesec_commons/stixifier/apps.py
dogesec_commons/stixifier/conf.py
dogesec_commons/stixifier/models.py
dogesec_commons/stixifier/serializers.py
dogesec_commons/stixifier/stixifier.py
dogesec_commons/stixifier/views.py
dogesec_commons/stixifier/migrations/0001_initial.py
dogesec_commons/stixifier/migrations/0002_profile_ai_content_check_variable.py
dogesec_commons/stixifier/migrations/0003_rename_ai_content_check_variable_profile_ai_content_check_provider_and_more.py
dogesec_commons/stixifier/migrations/0004_profile_identity_id.py
dogesec_commons/stixifier/migrations/0005_profile_generate_pdf.py
dogesec_commons/stixifier/migrations/0006_alter_profile_ai_create_attack_flow.py
dogesec_commons/stixifier/migrations/0007_remove_profile_ai_summary_provider_and_more.py
dogesec_commons/stixifier/migrations/0008_profile_ai_create_attack_navigator_layer.py
dogesec_commons/stixifier/migrations/0009_profile_include_embedded_relationships_attributes.py
dogesec_commons/stixifier/migrations/__init__.py
dogesec_commons/utils/__init__.py
dogesec_commons/utils/autoschema.py
dogesec_commons/utils/exceptions.py
dogesec_commons/utils/filters.py
dogesec_commons/utils/ordering.py
dogesec_commons/utils/pagination.py
dogesec_commons/utils/schemas.py
dogesec_commons/utils/serializers.py
dogesec_commons-1.3.4.dist-info/METADATA
dogesec_commons-1.3.4.dist-info/WHEEL
dogesec_commons-1.3.4.dist-info/licenses/LICENSE
dogesec_commons-1.3.4.dist-info/RECORD
